client/__init__.py
client/setup.py
client/client/__init__.py
client/client/client.py
client/client/client/__init__.py
client/client/client/add_contact.py
client/client/client/client_dbase.py
client/client/client/del_contact.py
client/client/client/main_window.py
client/client/client/main_window_conv.py
client/client/client/start_dialog.py
client/client/client/transport.py
client/client/doc/__init__.py
client/client/doc/build/__init__.py
client/client/doc/source/__init__.py
client/client/doc/source/conf.py
client/client/logs/__init__.py
client/client/logs/config_client_log.py
client/client/logs/config_server_log.py
client/client/soc_settings/__init__.py
client/client/soc_settings/config.py
client/client/soc_settings/decorator.py
client/client/soc_settings/descr.py
client/client/soc_settings/errors.py
client/client/soc_settings/mclasses.py
client/client/soc_settings/utils.py
client/client/unittests/__init__.py
client/client/unittests/test_client.py
client/client/unittests/test_utils.py
server/__init__.py
server/setup.py
server/server/__init__.py
server/server/server.py
server/server/starter.py
server/server/doc/__init__.py
server/server/doc/build/__init__.py
server/server/doc/source/__init__.py
server/server/doc/source/conf.py
server/server/logs/__init__.py
server/server/logs/config_client_log.py
server/server/logs/config_server_log.py
server/server/server/__init__.py
server/server/server/add_user.py
server/server/server/config_window.py
server/server/server/core.py
server/server/server/main_window.py
server/server/server/remove_user.py
server/server/server/server_dbase.py
server/server/server/stat_window.py
server/server/soc_settings/__init__.py
server/server/soc_settings/config.py
server/server/soc_settings/decorator.py
server/server/soc_settings/descr.py
server/server/soc_settings/errors.py
server/server/soc_settings/mclasses.py
server/server/soc_settings/utils.py
server/server/unittests/__init__.py
server/server/unittests/test_client.py
m_client-0.0.1.dist-info/METADATA
m_client-0.0.1.dist-info/WHEEL
m_client-0.0.1.dist-info/top_level.txt
m_client-0.0.1.dist-info/RECORD
