Metadata-Version: 1.0
Name: m_client
Version: 0.0.1
Summary: m_client
Home-page: UNKNOWN
Author: Sergei Chaban
Author-email: s_chaban@mail.ru
License: UNKNOWN
Platform: UNKNOWN
